qek/__init__.py
qek/data/__init__.py
qek/data/extractors.py
qek/data/graphs.py
qek/data/processed_data.py
qek/data/training_data.py
qek/kernel/__init__.py
qek/kernel/kernel.py
qek/shared/__init__.py
qek/shared/_utils.py
qek/shared/error.py
qek/shared/retrier.py
qek/target/__init__.py
qek/target/backends.py
qek/target/targets.py
quantum_evolution_kernel-0.3.4.dist-info/METADATA
quantum_evolution_kernel-0.3.4.dist-info/WHEEL
quantum_evolution_kernel-0.3.4.dist-info/licenses/LICENSE
quantum_evolution_kernel-0.3.4.dist-info/RECORD
