Metadata-Version: 2.4
Name: quantum-evolution-kernel
Version: 0.3.4
Summary: A Python library designed for the machine learning community to help users design quantum-driven similarity metrics for graphs and to use them inside kernel-based machine learning algorithms for graph data.ide the right environment to explore new ideas - both in terms of methodologies and data domain - while always interacting with a simple and intuitive QPU interface.
Project-URL: Issues, https://github.com/pasqal-io/quantum-evolution-kernel/issues
Project-URL: Source, https://github.com/pasqal-io/quantum-evolution-kernel
Author-email: Shaheen Acheche <shaheen.acheche@pasqal.com>, Roland Guichard <roland.guichard@pasqal.com>, David Teller <david.teller@pasqal.com>, Manu Lahariya <manu.lahariya@pasqal.com>
License: MIT-derived
License-File: LICENSE
Keywords: quantum
Classifier: Development Status :: 3 - Alpha
Classifier: Programming Language :: Python
Classifier: Programming Language :: Python :: 3.10
Classifier: Programming Language :: Python :: 3.11
Classifier: Programming Language :: Python :: 3.12
Classifier: Programming Language :: Python :: Implementation :: CPython
Classifier: Programming Language :: Python :: Implementation :: PyPy
Requires-Python: <=3.13,>=3.10
Requires-Dist: emu-mps~=2.2.0
Requires-Dist: matplotlib
Requires-Dist: networkx
Requires-Dist: numpy
Requires-Dist: pasqal-cloud
Requires-Dist: pulser~=1.5
Requires-Dist: rdkit
Requires-Dist: scikit-learn
Requires-Dist: torch
Requires-Dist: torch-geometric
Provides-Extra: extras
Requires-Dist: jupyter; extra == 'extras'
Requires-Dist: tqdm; extra == 'extras'
